AIArena/AI.py
AIArena/Human.py
AIArena/Ref.py
AIArena/Websockets.py
AIArena/__init__.py
AIArena/upload.py
AIArena/games/Ants.py
AIArena/games/Arena-old.py
AIArena/games/Arena.py
AIArena/games/BattleTanks.py
AIArena/games/Connect4.py
AIArena/games/GymBlackjack.py
AIArena/games/GymFrozenLake.py
AIArena/games/SpaceFighter.py
AIArena/games/StockMarket.py
AIArena/games/__init__.py
AIArena-0.0.61.dist-info/LICENSE
AIArena-0.0.61.dist-info/METADATA
AIArena-0.0.61.dist-info/WHEEL
AIArena-0.0.61.dist-info/top_level.txt
AIArena-0.0.61.dist-info/RECORD
