Metadata-Version: 2.1
Name: AIArena
Version: 0.0.61
Summary: AIArena beta
Home-page: https://github.com/tristan-neateworks/AIArena
Author: Tristan Neate
Author-email: tristan@neateworks.com
License: UNKNOWN
Platform: UNKNOWN
Classifier: Programming Language :: Python :: 3
Classifier: License :: OSI Approved :: MIT License
Classifier: Operating System :: OS Independent
Requires-Python: >=3.6
Requires-Dist: requests
Requires-Dist: dill
Requires-Dist: Websockets
